convclasses/__init__.py
convclasses/_compat.py
convclasses/converters.py
convclasses/disambiguators.py
convclasses/function_dispatch.py
convclasses/gen.py
convclasses/modifiers.py
convclasses/multistrategy_dispatch.py
convclasses-2.0.0.dist-info/LICENSE
convclasses-2.0.0.dist-info/METADATA
convclasses-2.0.0.dist-info/WHEEL
convclasses-2.0.0.dist-info/top_level.txt
convclasses-2.0.0.dist-info/RECORD
