Metadata-Version: 2.1
Name: convclasses
Version: 2.0.0
Summary: Complex custom class converters for dataclasses
Home-page: https://github.com/zeburek/convclasses
Author: Parviz Khavari
Author-email: me@parviz.pw
License: MIT license
Keywords: convclasses
Platform: UNKNOWN
Classifier: Development Status :: 5 - Production/Stable
Classifier: Intended Audience :: Developers
Classifier: License :: OSI Approved :: MIT License
Classifier: Natural Language :: English
Classifier: Programming Language :: Python :: 3.7
Classifier: Programming Language :: Python :: 3.8
Classifier: Programming Language :: Python :: 3.9
Requires-Python: ~=3.7
Provides-Extra: dev
